alibabacloud_rocketmq20220801/__init__.py
alibabacloud_rocketmq20220801/client.py
alibabacloud_rocketmq20220801/models/__init__.py
alibabacloud_rocketmq20220801/models/_add_disaster_recovery_item_request.py
alibabacloud_rocketmq20220801/models/_add_disaster_recovery_item_response.py
alibabacloud_rocketmq20220801/models/_add_disaster_recovery_item_response_body.py
alibabacloud_rocketmq20220801/models/_change_resource_group_request.py
alibabacloud_rocketmq20220801/models/_change_resource_group_response.py
alibabacloud_rocketmq20220801/models/_change_resource_group_response_body.py
alibabacloud_rocketmq20220801/models/_create_consumer_group_request.py
alibabacloud_rocketmq20220801/models/_create_consumer_group_response.py
alibabacloud_rocketmq20220801/models/_create_consumer_group_response_body.py
alibabacloud_rocketmq20220801/models/_create_disaster_recovery_plan_request.py
alibabacloud_rocketmq20220801/models/_create_disaster_recovery_plan_response.py
alibabacloud_rocketmq20220801/models/_create_disaster_recovery_plan_response_body.py
alibabacloud_rocketmq20220801/models/_create_instance_account_request.py
alibabacloud_rocketmq20220801/models/_create_instance_account_response.py
alibabacloud_rocketmq20220801/models/_create_instance_account_response_body.py
alibabacloud_rocketmq20220801/models/_create_instance_acl_request.py
alibabacloud_rocketmq20220801/models/_create_instance_acl_response.py
alibabacloud_rocketmq20220801/models/_create_instance_acl_response_body.py
alibabacloud_rocketmq20220801/models/_create_instance_ip_whitelist_request.py
alibabacloud_rocketmq20220801/models/_create_instance_ip_whitelist_response.py
alibabacloud_rocketmq20220801/models/_create_instance_ip_whitelist_response_body.py
alibabacloud_rocketmq20220801/models/_create_instance_request.py
alibabacloud_rocketmq20220801/models/_create_instance_response.py
alibabacloud_rocketmq20220801/models/_create_instance_response_body.py
alibabacloud_rocketmq20220801/models/_create_topic_request.py
alibabacloud_rocketmq20220801-5.0.2.dist-info/LICENSE
alibabacloud_rocketmq20220801-5.0.2.dist-info/METADATA
alibabacloud_rocketmq20220801-5.0.2.dist-info/WHEEL
alibabacloud_rocketmq20220801-5.0.2.dist-info/top_level.txt
alibabacloud_rocketmq20220801-5.0.2.dist-info/RECORD
